{
  "batchMeta": {
    "sourceDocumentCode": "MCRP 3-40D.12",
    "sourceDocumentTitle": "Construction Estimating",
    "sourceDocumentFull": "NTRP 4-04.2.3 / TM 3-34.41 / MCRP 3-40D.12",
    "sourceEdition": "October 2021, Change 1 October 2022",
    "division": "22",
    "divisionName": "Plumbing",
    "figure": "Figure 5-N-9",
    "figureTitle": "Cast Iron Pipe and Fittings ................................................................................................... 5-N-7",
    "extractedAt": "2026-06-10",
    "sourceCsv": "figure_5_N_9.csv"
  },
  "records": [
    {
      "sourceDocumentCode": "MCRP 3-40D.12",
      "division": "22",
      "divisionName": "Plumbing",
      "figure": "Figure 5-N-9",
      "figureTitle": "Cast Iron Pipe and Fittings ................................................................................................... 5-N-7",
      "workElementNumber": "22 11 19.64",
      "workElementLineNumber": "0010",
      "activityName": "Water Piping Specialties",
      "description": "Yard hydrant, all types",
      "unitOfMeasure": "Each",
      "manHoursPerUnit": 1.143,
      "crewSize": null,
      "skilledTrade": null,
      "laborerCount": null,
      "equipment": null,
      "notes": null,
      "sourcePage": "5-N-9",
      "sourcePdfPage": null,
      "confidence": "raw",
      "fabricateHours": 1.143,
      "erectStripHours": null,
      "cleanMoveHours": null,
      "extractionWarnings": []
    },
    {
      "sourceDocumentCode": "MCRP 3-40D.12",
      "division": "22",
      "divisionName": "Plumbing",
      "figure": "Figure 5-N-9",
      "figureTitle": "Cast Iron Pipe and Fittings ................................................................................................... 5-N-7",
      "workElementNumber": "22 13 29.14",
      "workElementLineNumber": "0160",
      "activityName": "Sanitary Sewerage Pumps (0160) Sewage ejector pump, 75 gallon, 12 gallons per minute",
      "description": "Sewage ejector pump, 75 gallon, 12 gallons per minute",
      "unitOfMeasure": "Each",
      "manHoursPerUnit": 6.67,
      "crewSize": null,
      "skilledTrade": null,
      "laborerCount": null,
      "equipment": null,
      "notes": null,
      "sourcePage": "5-N-9",
      "sourcePdfPage": null,
      "confidence": "raw",
      "fabricateHours": 6.67,
      "erectStripHours": null,
      "cleanMoveHours": null,
      "extractionWarnings": []
    },
    {
      "sourceDocumentCode": "MCRP 3-40D.12",
      "division": "22",
      "divisionName": "Plumbing",
      "figure": "Figure 5-N-9",
      "figureTitle": "Cast Iron Pipe and Fittings ................................................................................................... 5-N-7",
      "workElementNumber": "22 14 29.00",
      "workElementLineNumber": "0010",
      "activityName": "Sump Pumps",
      "description": "Cellar drainer, pedestal, 1/3 horsepower, standard",
      "unitOfMeasure": "Each",
      "manHoursPerUnit": 3.547,
      "crewSize": null,
      "skilledTrade": null,
      "laborerCount": null,
      "equipment": null,
      "notes": null,
      "sourcePage": "5-N-9",
      "sourcePdfPage": null,
      "confidence": "raw",
      "fabricateHours": 3.547,
      "erectStripHours": null,
      "cleanMoveHours": null,
      "extractionWarnings": []
    },
    {
      "sourceDocumentCode": "MCRP 3-40D.12",
      "division": "22",
      "divisionName": "Plumbing",
      "figure": "Figure 5-N-9",
      "figureTitle": "Cast Iron Pipe and Fittings ................................................................................................... 5-N-7",
      "workElementNumber": null,
      "workElementLineNumber": null,
      "activityName": "Minimum suggested crew size: one utilitiesman and one laborer.",
      "description": null,
      "unitOfMeasure": "Each",
      "manHoursPerUnit": null,
      "crewSize": null,
      "skilledTrade": null,
      "laborerCount": null,
      "equipment": null,
      "notes": null,
      "sourcePage": "5-N-9",
      "sourcePdfPage": null,
      "confidence": "needs_review",
      "fabricateHours": null,
      "erectStripHours": null,
      "cleanMoveHours": null,
      "extractionWarnings": [
        "Missing numeric man-hours per unit",
        "Missing work element line number",
        "Missing MasterFormat work element number"
      ]
    },
    {
      "sourceDocumentCode": "MCRP 3-40D.12",
      "division": "22",
      "divisionName": "Plumbing",
      "figure": "Figure 5-N-9",
      "figureTitle": "Cast Iron Pipe and Fittings ................................................................................................... 5-N-7",
      "workElementNumber": null,
      "workElementLineNumber": null,
      "activityName": "Note: Installation of specialties includes unloading, storing at site, handling into place, and installing fastening devices, including drilling, plugging, anchoring, and leveling as needed.",
      "description": null,
      "unitOfMeasure": "Each",
      "manHoursPerUnit": null,
      "crewSize": null,
      "skilledTrade": null,
      "laborerCount": null,
      "equipment": null,
      "notes": null,
      "sourcePage": "5-N-9",
      "sourcePdfPage": null,
      "confidence": "needs_review",
      "fabricateHours": null,
      "erectStripHours": null,
      "cleanMoveHours": null,
      "extractionWarnings": [
        "Missing numeric man-hours per unit",
        "Missing work element line number",
        "Missing MasterFormat work element number"
      ]
    },
    {
      "sourceDocumentCode": "MCRP 3-40D.12",
      "division": "22",
      "divisionName": "Plumbing",
      "figure": "Figure 5-N-9",
      "figureTitle": "Cast Iron Pipe and Fittings ................................................................................................... 5-N-7",
      "workElementNumber": "22 13 16.20",
      "workElementLineNumber": null,
      "activityName": "Cast Iron Pipe",
      "description": "22 13 16.20 Cast Iron Pipe",
      "unitOfMeasure": "Each",
      "manHoursPerUnit": null,
      "crewSize": null,
      "skilledTrade": null,
      "laborerCount": null,
      "equipment": null,
      "notes": null,
      "sourcePage": "5-N-9",
      "sourcePdfPage": null,
      "confidence": "needs_review",
      "fabricateHours": null,
      "erectStripHours": null,
      "cleanMoveHours": null,
      "extractionWarnings": [
        "Missing numeric man-hours per unit",
        "Missing work element line number"
      ]
    },
    {
      "sourceDocumentCode": "MCRP 3-40D.12",
      "division": "22",
      "divisionName": "Plumbing",
      "figure": "Figure 5-N-9",
      "figureTitle": "Cast Iron Pipe and Fittings ................................................................................................... 5-N-7",
      "workElementNumber": null,
      "workElementLineNumber": null,
      "activityName": "Pipe, single hub, service weight, lead and oakum joints 10 feet on center lead for caulking, oakum for caulking No hub, couplings 10 feet on center Bends Combination wyes, tees Reducing wyes, tees/combination 1 1/4 to 1 1/2 to 2 tees, tapped Crosses, tapped Reducers Plugs, clean-out traps, closet Bends",
      "description": null,
      "unitOfMeasure": "LF",
      "manHoursPerUnit": null,
      "crewSize": null,
      "skilledTrade": null,
      "laborerCount": null,
      "equipment": null,
      "notes": null,
      "sourcePage": "5-N-9",
      "sourcePdfPage": null,
      "confidence": "needs_review",
      "fabricateHours": null,
      "erectStripHours": null,
      "cleanMoveHours": null,
      "extractionWarnings": [
        "Missing numeric man-hours per unit",
        "Missing work element line number",
        "Missing MasterFormat work element number"
      ]
    },
    {
      "sourceDocumentCode": "MCRP 3-40D.12",
      "division": "22",
      "divisionName": "Plumbing",
      "figure": "Figure 5-N-9",
      "figureTitle": "Cast Iron Pipe and Fittings ................................................................................................... 5-N-7",
      "workElementNumber": null,
      "workElementLineNumber": null,
      "activityName": "Minimum suggested crew size: one utilitiesman and one laborer.",
      "description": null,
      "unitOfMeasure": "Each",
      "manHoursPerUnit": null,
      "crewSize": null,
      "skilledTrade": null,
      "laborerCount": null,
      "equipment": null,
      "notes": null,
      "sourcePage": "5-N-9",
      "sourcePdfPage": null,
      "confidence": "needs_review",
      "fabricateHours": null,
      "erectStripHours": null,
      "cleanMoveHours": null,
      "extractionWarnings": [
        "Missing numeric man-hours per unit",
        "Missing work element line number",
        "Missing MasterFormat work element number"
      ]
    },
    {
      "sourceDocumentCode": "MCRP 3-40D.12",
      "division": "22",
      "divisionName": "Plumbing",
      "figure": "Figure 5-N-9",
      "figureTitle": "Cast Iron Pipe and Fittings ................................................................................................... 5-N-7",
      "workElementNumber": null,
      "workElementLineNumber": null,
      "activityName": "Notes: 1. Primarily used for facility sanitary waste and vent piping. 2. Lifting equipment will be required on larger sizes. 3. The installation of cast-iron drains includes caulking and leading joints, plumbing and grading pipe, installing pipe hangers and straps, cutting pipe, and installing fittings.",
      "description": null,
      "unitOfMeasure": "Each",
      "manHoursPerUnit": null,
      "crewSize": null,
      "skilledTrade": null,
      "laborerCount": null,
      "equipment": null,
      "notes": null,
      "sourcePage": "5-N-9",
      "sourcePdfPage": null,
      "confidence": "needs_review",
      "fabricateHours": null,
      "erectStripHours": null,
      "cleanMoveHours": null,
      "extractionWarnings": [
        "Missing numeric man-hours per unit",
        "Missing work element line number",
        "Missing MasterFormat work element number"
      ]
    }
  ]
}