{
  "batchMeta": {
    "sourceDocumentCode": "MCRP 3-40D.12",
    "sourceDocumentTitle": "Construction Estimating",
    "sourceDocumentFull": "NTRP 4-04.2.3 / TM 3-34.41 / MCRP 3-40D.12",
    "sourceEdition": "October 2021, Change 1 October 2022",
    "division": "22",
    "divisionName": "Plumbing",
    "figure": "Figure 5-N-11",
    "figureTitle": "Finished Plumbing",
    "extractedAt": "2026-06-10",
    "sourceCsv": "figure_5_N_11.csv",
    "annexKWarning": null
  },
  "records": [
    {
      "id": "22-32-19.10-0510",
      "sourceDocumentCode": "MCRP 3-40D.12",
      "sourceDocumentTitle": "Construction Estimating",
      "sourceDocumentFull": "NTRP 4-04.2.3 / TM 3-34.41 / MCRP 3-40D.12",
      "sourceEdition": "October 2021, Change 1 October 2022",
      "division": "22",
      "divisionName": "Plumbing",
      "figure": "Figure 5-N-11",
      "figureTitle": "Finished Plumbing",
      "sourcePage": "5-N-11",
      "sourcePdfPage": 14,
      "workElementNumber": "22 32 19.10",
      "workElementLineNumber": "0510",
      "category": "Water Filters (0510) Diatomite filter, 660 gallons per hour, 1 inch pipe",
      "subcategory": "Diatomite filter, 660 gallons per hour",
      "activityName": "Diatomite filter, 660 gallons per hour, 1 inch pipe",
      "description": "1 inch pipe",
      "unitOfMeasure": "Each",
      "manHoursPerUnit": 10.6667,
      "fabricateHours": 10.6667,
      "erectStripHours": null,
      "cleanMoveHours": null,
      "crewSize": null,
      "skilledTrade": null,
      "skilledCount": null,
      "laborerCount": null,
      "equipmentOperatorCount": null,
      "equipment": null,
      "figureCrewNotes": null,
      "figureNotes": null,
      "rowNotes": null,
      "qaStatus": "raw",
      "extractionWarnings": [],
      "createdAt": "2026-06-10T09:41:49+00:00",
      "updatedAt": "2026-06-10T09:41:49+00:00"
    },
    {
      "id": "22-32-33.00-0010",
      "sourceDocumentCode": "MCRP 3-40D.12",
      "sourceDocumentTitle": "Construction Estimating",
      "sourceDocumentFull": "NTRP 4-04.2.3 / TM 3-34.41 / MCRP 3-40D.12",
      "sourceEdition": "October 2021, Change 1 October 2022",
      "division": "22",
      "divisionName": "Plumbing",
      "figure": "Figure 5-N-11",
      "figureTitle": "Finished Plumbing",
      "sourcePage": "5-N-11",
      "sourcePdfPage": 14,
      "workElementNumber": "22 32 33.00",
      "workElementLineNumber": "0010",
      "category": "Water Heaters",
      "subcategory": "Electric or gas",
      "activityName": "Electric or gas, 30 gallons",
      "description": "30 gallons",
      "unitOfMeasure": "Each",
      "manHoursPerUnit": 4.256,
      "fabricateHours": 4.256,
      "erectStripHours": null,
      "cleanMoveHours": null,
      "crewSize": null,
      "skilledTrade": null,
      "skilledCount": null,
      "laborerCount": null,
      "equipmentOperatorCount": null,
      "equipment": null,
      "figureCrewNotes": null,
      "figureNotes": null,
      "rowNotes": null,
      "qaStatus": "raw",
      "extractionWarnings": [],
      "createdAt": "2026-06-10T09:41:49+00:00",
      "updatedAt": "2026-06-10T09:41:49+00:00"
    },
    {
      "id": "22-32-33.00-0020",
      "sourceDocumentCode": "MCRP 3-40D.12",
      "sourceDocumentTitle": "Construction Estimating",
      "sourceDocumentFull": "NTRP 4-04.2.3 / TM 3-34.41 / MCRP 3-40D.12",
      "sourceEdition": "October 2021, Change 1 October 2022",
      "division": "22",
      "divisionName": "Plumbing",
      "figure": "Figure 5-N-11",
      "figureTitle": "Finished Plumbing",
      "sourcePage": "5-N-11",
      "sourcePdfPage": 14,
      "workElementNumber": "22 32 33.00",
      "workElementLineNumber": "0020",
      "category": "Water Heaters",
      "subcategory": "Water Heaters",
      "activityName": "Water Heaters, 80 gallons",
      "description": "80 gallons",
      "unitOfMeasure": "Each",
      "manHoursPerUnit": 21.28,
      "fabricateHours": 21.28,
      "erectStripHours": null,
      "cleanMoveHours": null,
      "crewSize": null,
      "skilledTrade": null,
      "skilledCount": null,
      "laborerCount": null,
      "equipmentOperatorCount": null,
      "equipment": null,
      "figureCrewNotes": null,
      "figureNotes": null,
      "rowNotes": null,
      "qaStatus": "raw",
      "extractionWarnings": [],
      "createdAt": "2026-06-10T09:41:49+00:00",
      "updatedAt": "2026-06-10T09:41:49+00:00"
    },
    {
      "id": "00-00-00.00-0000",
      "sourceDocumentCode": "MCRP 3-40D.12",
      "sourceDocumentTitle": "Construction Estimating",
      "sourceDocumentFull": "NTRP 4-04.2.3 / TM 3-34.41 / MCRP 3-40D.12",
      "sourceEdition": "October 2021, Change 1 October 2022",
      "division": "22",
      "divisionName": "Plumbing",
      "figure": "Figure 5-N-11",
      "figureTitle": "Finished Plumbing",
      "sourcePage": "5-N-11",
      "sourcePdfPage": 14,
      "workElementNumber": null,
      "workElementLineNumber": null,
      "category": null,
      "subcategory": "Minimum suggested crew size: one utilitiesman and one laborer.",
      "activityName": "Minimum suggested crew size: one utilitiesman and one laborer.",
      "description": null,
      "unitOfMeasure": "Each",
      "manHoursPerUnit": null,
      "fabricateHours": null,
      "erectStripHours": null,
      "cleanMoveHours": null,
      "crewSize": null,
      "skilledTrade": null,
      "skilledCount": null,
      "laborerCount": null,
      "equipmentOperatorCount": null,
      "equipment": null,
      "figureCrewNotes": null,
      "figureNotes": null,
      "rowNotes": null,
      "qaStatus": "needs_review",
      "extractionWarnings": [
        "Missing numeric man-hours per unit",
        "Missing work element line number",
        "Missing MasterFormat work element number"
      ],
      "createdAt": "2026-06-10T09:41:49+00:00",
      "updatedAt": "2026-06-10T09:41:49+00:00"
    },
    {
      "id": "00-00-00.00-0000",
      "sourceDocumentCode": "MCRP 3-40D.12",
      "sourceDocumentTitle": "Construction Estimating",
      "sourceDocumentFull": "NTRP 4-04.2.3 / TM 3-34.41 / MCRP 3-40D.12",
      "sourceEdition": "October 2021, Change 1 October 2022",
      "division": "22",
      "divisionName": "Plumbing",
      "figure": "Figure 5-N-11",
      "figureTitle": "Finished Plumbing",
      "sourcePage": "5-N-11",
      "sourcePdfPage": 14,
      "workElementNumber": null,
      "workElementLineNumber": null,
      "category": null,
      "subcategory": "Note: Installation of specialties includes unloading",
      "activityName": "Note: Installation of specialties includes unloading, storing at site, handling into place, and installing fastening devices, including drilling, plugging, anchoring, and leveling as needed.",
      "description": "storing at site, handling into place, and installing fastening devices, including drilling, plugging, anchoring, and leveling as needed.",
      "unitOfMeasure": "Each",
      "manHoursPerUnit": null,
      "fabricateHours": null,
      "erectStripHours": null,
      "cleanMoveHours": null,
      "crewSize": null,
      "skilledTrade": null,
      "skilledCount": null,
      "laborerCount": null,
      "equipmentOperatorCount": null,
      "equipment": null,
      "figureCrewNotes": null,
      "figureNotes": null,
      "rowNotes": null,
      "qaStatus": "needs_review",
      "extractionWarnings": [
        "Missing numeric man-hours per unit",
        "Missing work element line number",
        "Missing MasterFormat work element number"
      ],
      "createdAt": "2026-06-10T09:41:49+00:00",
      "updatedAt": "2026-06-10T09:41:49+00:00"
    },
    {
      "id": "22-41-13.40-0000",
      "sourceDocumentCode": "MCRP 3-40D.12",
      "sourceDocumentTitle": "Construction Estimating",
      "sourceDocumentFull": "NTRP 4-04.2.3 / TM 3-34.41 / MCRP 3-40D.12",
      "sourceEdition": "October 2021, Change 1 October 2022",
      "division": "22",
      "divisionName": "Plumbing",
      "figure": "Figure 5-N-11",
      "figureTitle": "Finished Plumbing",
      "sourcePage": "5-N-11",
      "sourcePdfPage": 14,
      "workElementNumber": "22 41 13.40",
      "workElementLineNumber": null,
      "category": "Water Closets Tank type, wall hung Floor mounted, one piece Bowl only, wall hung Bowl only, floor mount Water conserving type",
      "subcategory": "22 41 13.40 Water Closets Tank type",
      "activityName": "22 41 13.40 Water Closets Tank type, wall hung Floor mounted, one piece Bowl only, wall hung Bowl only, floor mount Water conserving type",
      "description": "wall hung Floor mounted, one piece Bowl only, wall hung Bowl only, floor mount Water conserving type",
      "unitOfMeasure": "Each",
      "manHoursPerUnit": null,
      "fabricateHours": null,
      "erectStripHours": null,
      "cleanMoveHours": null,
      "crewSize": null,
      "skilledTrade": null,
      "skilledCount": null,
      "laborerCount": null,
      "equipmentOperatorCount": null,
      "equipment": null,
      "figureCrewNotes": null,
      "figureNotes": null,
      "rowNotes": null,
      "qaStatus": "needs_review",
      "extractionWarnings": [
        "Missing numeric man-hours per unit",
        "Missing work element line number"
      ],
      "createdAt": "2026-06-10T09:41:49+00:00",
      "updatedAt": "2026-06-10T09:41:49+00:00"
    },
    {
      "id": "22-41-16.10-0000",
      "sourceDocumentCode": "MCRP 3-40D.12",
      "sourceDocumentTitle": "Construction Estimating",
      "sourceDocumentFull": "NTRP 4-04.2.3 / TM 3-34.41 / MCRP 3-40D.12",
      "sourceEdition": "October 2021, Change 1 October 2022",
      "division": "22",
      "divisionName": "Plumbing",
      "figure": "Figure 5-N-11",
      "figureTitle": "Finished Plumbing",
      "sourcePage": "5-N-11",
      "sourcePdfPage": 14,
      "workElementNumber": "22 41 16.10",
      "workElementLineNumber": null,
      "category": "Lavatories Vanity top Wall hung",
      "subcategory": "22 41 16.10 Lavatories Vanity top Wall hung",
      "activityName": "22 41 16.10 Lavatories Vanity top Wall hung",
      "description": null,
      "unitOfMeasure": "Each",
      "manHoursPerUnit": null,
      "fabricateHours": null,
      "erectStripHours": null,
      "cleanMoveHours": null,
      "crewSize": null,
      "skilledTrade": null,
      "skilledCount": null,
      "laborerCount": null,
      "equipmentOperatorCount": null,
      "equipment": null,
      "figureCrewNotes": null,
      "figureNotes": null,
      "rowNotes": null,
      "qaStatus": "needs_review",
      "extractionWarnings": [
        "Missing numeric man-hours per unit",
        "Missing work element line number"
      ],
      "createdAt": "2026-06-10T09:41:49+00:00",
      "updatedAt": "2026-06-10T09:41:49+00:00"
    },
    {
      "id": "22-41-16.30-0000",
      "sourceDocumentCode": "MCRP 3-40D.12",
      "sourceDocumentTitle": "Construction Estimating",
      "sourceDocumentFull": "NTRP 4-04.2.3 / TM 3-34.41 / MCRP 3-40D.12",
      "sourceEdition": "October 2021, Change 1 October 2022",
      "division": "22",
      "divisionName": "Plumbing",
      "figure": "Figure 5-N-11",
      "figureTitle": "Finished Plumbing",
      "sourcePage": "5-N-11",
      "sourcePdfPage": 14,
      "workElementNumber": "22 41 16.30",
      "workElementLineNumber": null,
      "category": "Sinks Corrosion resistant Kitchen, countertop Kitchen, raised deck",
      "subcategory": "22 41 16.30 Sinks Corrosion resistant Kitchen",
      "activityName": "22 41 16.30 Sinks Corrosion resistant Kitchen, countertop Kitchen, raised deck",
      "description": "countertop Kitchen, raised deck",
      "unitOfMeasure": "Each",
      "manHoursPerUnit": null,
      "fabricateHours": null,
      "erectStripHours": null,
      "cleanMoveHours": null,
      "crewSize": null,
      "skilledTrade": null,
      "skilledCount": null,
      "laborerCount": null,
      "equipmentOperatorCount": null,
      "equipment": null,
      "figureCrewNotes": null,
      "figureNotes": null,
      "rowNotes": null,
      "qaStatus": "needs_review",
      "extractionWarnings": [
        "Missing numeric man-hours per unit",
        "Missing work element line number"
      ],
      "createdAt": "2026-06-10T09:41:49+00:00",
      "updatedAt": "2026-06-10T09:41:49+00:00"
    },
    {
      "id": "00-00-00.00-0000",
      "sourceDocumentCode": "MCRP 3-40D.12",
      "sourceDocumentTitle": "Construction Estimating",
      "sourceDocumentFull": "NTRP 4-04.2.3 / TM 3-34.41 / MCRP 3-40D.12",
      "sourceEdition": "October 2021, Change 1 October 2022",
      "division": "22",
      "divisionName": "Plumbing",
      "figure": "Figure 5-N-11",
      "figureTitle": "Finished Plumbing",
      "sourcePage": "5-N-11",
      "sourcePdfPage": 14,
      "workElementNumber": null,
      "workElementLineNumber": null,
      "category": null,
      "subcategory": "Minimum suggested crew size: one utilitiesman and one laborer.",
      "activityName": "Minimum suggested crew size: one utilitiesman and one laborer.",
      "description": null,
      "unitOfMeasure": "Each",
      "manHoursPerUnit": null,
      "fabricateHours": null,
      "erectStripHours": null,
      "cleanMoveHours": null,
      "crewSize": null,
      "skilledTrade": null,
      "skilledCount": null,
      "laborerCount": null,
      "equipmentOperatorCount": null,
      "equipment": null,
      "figureCrewNotes": null,
      "figureNotes": null,
      "rowNotes": null,
      "qaStatus": "needs_review",
      "extractionWarnings": [
        "Missing numeric man-hours per unit",
        "Missing work element line number",
        "Missing MasterFormat work element number"
      ],
      "createdAt": "2026-06-10T09:41:49+00:00",
      "updatedAt": "2026-06-10T09:41:49+00:00"
    },
    {
      "id": "00-00-00.00-0000",
      "sourceDocumentCode": "MCRP 3-40D.12",
      "sourceDocumentTitle": "Construction Estimating",
      "sourceDocumentFull": "NTRP 4-04.2.3 / TM 3-34.41 / MCRP 3-40D.12",
      "sourceEdition": "October 2021, Change 1 October 2022",
      "division": "22",
      "divisionName": "Plumbing",
      "figure": "Figure 5-N-11",
      "figureTitle": "Finished Plumbing",
      "sourcePage": "5-N-11",
      "sourcePdfPage": 14,
      "workElementNumber": null,
      "workElementLineNumber": null,
      "category": null,
      "subcategory": "Notes: 1. Rough-in includes supply",
      "activityName": "Notes: 1. Rough-in includes supply, waste, and vent piping. 2. Work includes setting and connecting all supply piping, plumbing fixtures, and trim.",
      "description": "waste, and vent piping. 2. Work includes setting and connecting all supply piping, plumbing fixtures, and trim.",
      "unitOfMeasure": "Each",
      "manHoursPerUnit": null,
      "fabricateHours": null,
      "erectStripHours": null,
      "cleanMoveHours": null,
      "crewSize": null,
      "skilledTrade": null,
      "skilledCount": null,
      "laborerCount": null,
      "equipmentOperatorCount": null,
      "equipment": null,
      "figureCrewNotes": null,
      "figureNotes": null,
      "rowNotes": null,
      "qaStatus": "needs_review",
      "extractionWarnings": [
        "Missing numeric man-hours per unit",
        "Missing work element line number",
        "Missing MasterFormat work element number"
      ],
      "createdAt": "2026-06-10T09:41:49+00:00",
      "updatedAt": "2026-06-10T09:41:49+00:00"
    },
    {
      "id": "22-41-19.10-0000",
      "sourceDocumentCode": "MCRP 3-40D.12",
      "sourceDocumentTitle": "Construction Estimating",
      "sourceDocumentFull": "NTRP 4-04.2.3 / TM 3-34.41 / MCRP 3-40D.12",
      "sourceEdition": "October 2021, Change 1 October 2022",
      "division": "22",
      "divisionName": "Plumbing",
      "figure": "Figure 5-N-11",
      "figureTitle": "Finished Plumbing",
      "sourcePage": "5-N-11",
      "sourcePdfPage": 14,
      "workElementNumber": "22 41 19.10",
      "workElementLineNumber": null,
      "category": "Bath Tubs",
      "subcategory": "22 41 19.10 Bath Tubs",
      "activityName": "22 41 19.10 Bath Tubs",
      "description": null,
      "unitOfMeasure": "Each",
      "manHoursPerUnit": null,
      "fabricateHours": null,
      "erectStripHours": null,
      "cleanMoveHours": null,
      "crewSize": null,
      "skilledTrade": null,
      "skilledCount": null,
      "laborerCount": null,
      "equipmentOperatorCount": null,
      "equipment": null,
      "figureCrewNotes": null,
      "figureNotes": null,
      "rowNotes": null,
      "qaStatus": "needs_review",
      "extractionWarnings": [
        "Missing numeric man-hours per unit",
        "Missing work element line number"
      ],
      "createdAt": "2026-06-10T09:41:49+00:00",
      "updatedAt": "2026-06-10T09:41:49+00:00"
    },
    {
      "id": "22-41-23.20-0000",
      "sourceDocumentCode": "MCRP 3-40D.12",
      "sourceDocumentTitle": "Construction Estimating",
      "sourceDocumentFull": "NTRP 4-04.2.3 / TM 3-34.41 / MCRP 3-40D.12",
      "sourceEdition": "October 2021, Change 1 October 2022",
      "division": "22",
      "divisionName": "Plumbing",
      "figure": "Figure 5-N-11",
      "figureTitle": "Finished Plumbing",
      "sourcePage": "5-N-11",
      "sourcePdfPage": 14,
      "workElementNumber": "22 41 23.20",
      "workElementLineNumber": null,
      "category": "Showers",
      "subcategory": "Showers",
      "activityName": "Showers, 22 41 23.20 Showers",
      "description": "22 41 23.20 Showers",
      "unitOfMeasure": "Each",
      "manHoursPerUnit": null,
      "fabricateHours": null,
      "erectStripHours": null,
      "cleanMoveHours": null,
      "crewSize": null,
      "skilledTrade": null,
      "skilledCount": null,
      "laborerCount": null,
      "equipmentOperatorCount": null,
      "equipment": null,
      "figureCrewNotes": null,
      "figureNotes": null,
      "rowNotes": null,
      "qaStatus": "needs_review",
      "extractionWarnings": [
        "Missing numeric man-hours per unit",
        "Missing work element line number"
      ],
      "createdAt": "2026-06-10T09:41:49+00:00",
      "updatedAt": "2026-06-10T09:41:49+00:00"
    },
    {
      "id": "22-41-36.10-0000",
      "sourceDocumentCode": "MCRP 3-40D.12",
      "sourceDocumentTitle": "Construction Estimating",
      "sourceDocumentFull": "NTRP 4-04.2.3 / TM 3-34.41 / MCRP 3-40D.12",
      "sourceEdition": "October 2021, Change 1 October 2022",
      "division": "22",
      "divisionName": "Plumbing",
      "figure": "Figure 5-N-11",
      "figureTitle": "Finished Plumbing",
      "sourcePage": "5-N-11",
      "sourcePdfPage": 14,
      "workElementNumber": "22 41 36.10",
      "workElementLineNumber": null,
      "category": "Laundry Sinks",
      "subcategory": "22 41 36.10 Laundry Sinks",
      "activityName": "22 41 36.10 Laundry Sinks",
      "description": null,
      "unitOfMeasure": "Each",
      "manHoursPerUnit": null,
      "fabricateHours": null,
      "erectStripHours": null,
      "cleanMoveHours": null,
      "crewSize": null,
      "skilledTrade": null,
      "skilledCount": null,
      "laborerCount": null,
      "equipmentOperatorCount": null,
      "equipment": null,
      "figureCrewNotes": null,
      "figureNotes": null,
      "rowNotes": null,
      "qaStatus": "needs_review",
      "extractionWarnings": [
        "Missing numeric man-hours per unit",
        "Missing work element line number"
      ],
      "createdAt": "2026-06-10T09:41:49+00:00",
      "updatedAt": "2026-06-10T09:41:49+00:00"
    },
    {
      "id": "22-42-13.30-0000",
      "sourceDocumentCode": "MCRP 3-40D.12",
      "sourceDocumentTitle": "Construction Estimating",
      "sourceDocumentFull": "NTRP 4-04.2.3 / TM 3-34.41 / MCRP 3-40D.12",
      "sourceEdition": "October 2021, Change 1 October 2022",
      "division": "22",
      "divisionName": "Plumbing",
      "figure": "Figure 5-N-11",
      "figureTitle": "Finished Plumbing",
      "sourcePage": "5-N-11",
      "sourcePdfPage": 14,
      "workElementNumber": "22 42 13.30",
      "workElementLineNumber": null,
      "category": "Urinals, Commercial Wall hung Stall type",
      "subcategory": "22 42 13.30 Urinals",
      "activityName": "22 42 13.30 Urinals, Commercial Wall hung Stall type",
      "description": "Commercial Wall hung Stall type",
      "unitOfMeasure": "Each",
      "manHoursPerUnit": null,
      "fabricateHours": null,
      "erectStripHours": null,
      "cleanMoveHours": null,
      "crewSize": null,
      "skilledTrade": null,
      "skilledCount": null,
      "laborerCount": null,
      "equipmentOperatorCount": null,
      "equipment": null,
      "figureCrewNotes": null,
      "figureNotes": null,
      "rowNotes": null,
      "qaStatus": "needs_review",
      "extractionWarnings": [
        "Missing numeric man-hours per unit",
        "Missing work element line number"
      ],
      "createdAt": "2026-06-10T09:41:49+00:00",
      "updatedAt": "2026-06-10T09:41:49+00:00"
    },
    {
      "id": "22-42-16.40-0000",
      "sourceDocumentCode": "MCRP 3-40D.12",
      "sourceDocumentTitle": "Construction Estimating",
      "sourceDocumentFull": "NTRP 4-04.2.3 / TM 3-34.41 / MCRP 3-40D.12",
      "sourceEdition": "October 2021, Change 1 October 2022",
      "division": "22",
      "divisionName": "Plumbing",
      "figure": "Figure 5-N-11",
      "figureTitle": "Finished Plumbing",
      "sourcePage": "5-N-11",
      "sourcePdfPage": 14,
      "workElementNumber": "22 42 16.40",
      "workElementLineNumber": null,
      "category": "Service Sinks Floor type Wall hung",
      "subcategory": "22 42 16.40 Service Sinks Floor type Wall hung",
      "activityName": "22 42 16.40 Service Sinks Floor type Wall hung",
      "description": null,
      "unitOfMeasure": "Each",
      "manHoursPerUnit": null,
      "fabricateHours": null,
      "erectStripHours": null,
      "cleanMoveHours": null,
      "crewSize": null,
      "skilledTrade": null,
      "skilledCount": null,
      "laborerCount": null,
      "equipmentOperatorCount": null,
      "equipment": null,
      "figureCrewNotes": null,
      "figureNotes": null,
      "rowNotes": null,
      "qaStatus": "needs_review",
      "extractionWarnings": [
        "Missing numeric man-hours per unit",
        "Missing work element line number"
      ],
      "createdAt": "2026-06-10T09:41:49+00:00",
      "updatedAt": "2026-06-10T09:41:49+00:00"
    },
    {
      "id": "22-47-13.10-0000",
      "sourceDocumentCode": "MCRP 3-40D.12",
      "sourceDocumentTitle": "Construction Estimating",
      "sourceDocumentFull": "NTRP 4-04.2.3 / TM 3-34.41 / MCRP 3-40D.12",
      "sourceEdition": "October 2021, Change 1 October 2022",
      "division": "22",
      "divisionName": "Plumbing",
      "figure": "Figure 5-N-11",
      "figureTitle": "Finished Plumbing",
      "sourcePage": "5-N-11",
      "sourcePdfPage": 14,
      "workElementNumber": "22 47 13.10",
      "workElementLineNumber": null,
      "category": "Drinking Water Fountains",
      "subcategory": "22 47 13.10 Drinking Water Fountains",
      "activityName": "22 47 13.10 Drinking Water Fountains",
      "description": null,
      "unitOfMeasure": "Each",
      "manHoursPerUnit": null,
      "fabricateHours": null,
      "erectStripHours": null,
      "cleanMoveHours": null,
      "crewSize": null,
      "skilledTrade": null,
      "skilledCount": null,
      "laborerCount": null,
      "equipmentOperatorCount": null,
      "equipment": null,
      "figureCrewNotes": null,
      "figureNotes": null,
      "rowNotes": null,
      "qaStatus": "needs_review",
      "extractionWarnings": [
        "Missing numeric man-hours per unit",
        "Missing work element line number"
      ],
      "createdAt": "2026-06-10T09:41:49+00:00",
      "updatedAt": "2026-06-10T09:41:49+00:00"
    },
    {
      "id": "22-47-16.10-0000",
      "sourceDocumentCode": "MCRP 3-40D.12",
      "sourceDocumentTitle": "Construction Estimating",
      "sourceDocumentFull": "NTRP 4-04.2.3 / TM 3-34.41 / MCRP 3-40D.12",
      "sourceEdition": "October 2021, Change 1 October 2022",
      "division": "22",
      "divisionName": "Plumbing",
      "figure": "Figure 5-N-11",
      "figureTitle": "Finished Plumbing",
      "sourcePage": "5-N-11",
      "sourcePdfPage": 14,
      "workElementNumber": "22 47 16.10",
      "workElementLineNumber": null,
      "category": "Electric Water Coolers",
      "subcategory": "22 47 16.10 Electric Water Coolers",
      "activityName": "22 47 16.10 Electric Water Coolers",
      "description": null,
      "unitOfMeasure": "Each",
      "manHoursPerUnit": null,
      "fabricateHours": null,
      "erectStripHours": null,
      "cleanMoveHours": null,
      "crewSize": null,
      "skilledTrade": null,
      "skilledCount": null,
      "laborerCount": null,
      "equipmentOperatorCount": null,
      "equipment": null,
      "figureCrewNotes": null,
      "figureNotes": null,
      "rowNotes": null,
      "qaStatus": "needs_review",
      "extractionWarnings": [
        "Missing numeric man-hours per unit",
        "Missing work element line number"
      ],
      "createdAt": "2026-06-10T09:41:49+00:00",
      "updatedAt": "2026-06-10T09:41:49+00:00"
    },
    {
      "id": "00-00-00.00-0000",
      "sourceDocumentCode": "MCRP 3-40D.12",
      "sourceDocumentTitle": "Construction Estimating",
      "sourceDocumentFull": "NTRP 4-04.2.3 / TM 3-34.41 / MCRP 3-40D.12",
      "sourceEdition": "October 2021, Change 1 October 2022",
      "division": "22",
      "divisionName": "Plumbing",
      "figure": "Figure 5-N-11",
      "figureTitle": "Finished Plumbing",
      "sourcePage": "5-N-11",
      "sourcePdfPage": 14,
      "workElementNumber": null,
      "workElementLineNumber": null,
      "category": null,
      "subcategory": "Minimum suggested crew size: one utilitiesman and one laborer.",
      "activityName": "Minimum suggested crew size: one utilitiesman and one laborer.",
      "description": null,
      "unitOfMeasure": "Each",
      "manHoursPerUnit": null,
      "fabricateHours": null,
      "erectStripHours": null,
      "cleanMoveHours": null,
      "crewSize": null,
      "skilledTrade": null,
      "skilledCount": null,
      "laborerCount": null,
      "equipmentOperatorCount": null,
      "equipment": null,
      "figureCrewNotes": null,
      "figureNotes": null,
      "rowNotes": null,
      "qaStatus": "needs_review",
      "extractionWarnings": [
        "Missing numeric man-hours per unit",
        "Missing work element line number",
        "Missing MasterFormat work element number"
      ],
      "createdAt": "2026-06-10T09:41:49+00:00",
      "updatedAt": "2026-06-10T09:41:49+00:00"
    },
    {
      "id": "00-00-00.00-0000",
      "sourceDocumentCode": "MCRP 3-40D.12",
      "sourceDocumentTitle": "Construction Estimating",
      "sourceDocumentFull": "NTRP 4-04.2.3 / TM 3-34.41 / MCRP 3-40D.12",
      "sourceEdition": "October 2021, Change 1 October 2022",
      "division": "22",
      "divisionName": "Plumbing",
      "figure": "Figure 5-N-11",
      "figureTitle": "Finished Plumbing",
      "sourcePage": "5-N-11",
      "sourcePdfPage": 14,
      "workElementNumber": null,
      "workElementLineNumber": null,
      "category": null,
      "subcategory": "Notes: 1. Rough-in includes supply",
      "activityName": "Notes: 1. Rough-in includes supply, waste, and vent piping. 2. Work includes setting and connecting all supply piping, plumbing fixtures, and trim.",
      "description": "waste, and vent piping. 2. Work includes setting and connecting all supply piping, plumbing fixtures, and trim.",
      "unitOfMeasure": "Each",
      "manHoursPerUnit": null,
      "fabricateHours": null,
      "erectStripHours": null,
      "cleanMoveHours": null,
      "crewSize": null,
      "skilledTrade": null,
      "skilledCount": null,
      "laborerCount": null,
      "equipmentOperatorCount": null,
      "equipment": null,
      "figureCrewNotes": null,
      "figureNotes": null,
      "rowNotes": null,
      "qaStatus": "needs_review",
      "extractionWarnings": [
        "Missing numeric man-hours per unit",
        "Missing work element line number",
        "Missing MasterFormat work element number"
      ],
      "createdAt": "2026-06-10T09:41:49+00:00",
      "updatedAt": "2026-06-10T09:41:49+00:00"
    }
  ]
}